{
  "headers": {
    "access-control-allow-origin": "*",
    "x-frame-options": "DENY",
    "date": "Sun, 29 Oct 2023 14:12:35 GMT",
    "server": "deno/gcp-europe-west2",
    "x-content-type-options": "nosniff",
    "content-length": "3198",
    "content-type": "application/typescript; charset=utf-8",
    "cross-origin-resource-policy": "same-origin",
    "cross-origin-embedder-policy": "same-origin",
    "etag": "\"749e046eecfe7c671f6e7c80ca798c29\"",
    "x-amz-replication-status": "COMPLETED",
    "x-amz-version-id": "ZsM3sDmQdYvfezJX3jSR1KesYtXwYd6z",
    "content-security-policy": "default-src 'none'; style-src 'unsafe-inline'; sandbox",
    "accept-ranges": "bytes",
    "cross-origin-opener-policy": "same-origin",
    "strict-transport-security": "max-age=63072000; includeSubDomains; preload",
    "cache-control": "public, max-age=31536000, immutable",
    "x-amz-cf-id": "nzdD1Datno6kh3JbG2beJa78f1MRL7H2zm4DqJfzR70FupckypcDeQ==",
    "age": "28410548",
    "last-modified": "Fri, 25 Mar 2022 13:32:48 GMT",
    "x-amz-cf-pop": "LHR50-P6",
    "referrer-policy": "strict-origin-when-cross-origin",
    "vary": "Accept-Encoding, Origin",
    "server-timing": "fetchSource;dur=78",
    "via": "http/2 edgeproxy-h",
    "x-cache": "Hit from cloudfront"
  },
  "url": "https://deno.land/std@0.132.0/node/_fs/_fs_open.ts",
  "now": {
    "secs_since_epoch": 1726999292,
    "nanos_since_epoch": 224355043
  }
}