{
  "headers": {
    "cross-origin-embedder-policy": "same-origin",
    "cross-origin-resource-policy": "same-origin",
    "date": "Sun, 29 Oct 2023 14:12:35 GMT",
    "referrer-policy": "strict-origin-when-cross-origin",
    "accept-ranges": "bytes",
    "last-modified": "Fri, 25 Mar 2022 13:32:48 GMT",
    "vary": "Accept-Encoding, Origin",
    "content-type": "application/typescript; charset=utf-8",
    "via": "http/2 edgeproxy-h",
    "strict-transport-security": "max-age=63072000; includeSubDomains; preload",
    "content-length": "4195",
    "cross-origin-opener-policy": "same-origin",
    "etag": "\"8d60f5701395448ace8f6d9ffa7c1ae5\"",
    "x-amz-cf-id": "a0QjWWqYT20LYIVzXTQju3GmOjM94DBBHSE2eeXmBo-s7sLV8l1fYg==",
    "access-control-allow-origin": "*",
    "x-amz-replication-status": "COMPLETED",
    "content-security-policy": "default-src 'none'; style-src 'unsafe-inline'; sandbox",
    "server-timing": "fetchSource;dur=154",
    "x-frame-options": "DENY",
    "x-amz-version-id": "s1LhjDAUrnSYzL2rV1dVDmUX6Zo1DYW6",
    "server": "deno/gcp-europe-west2",
    "x-amz-cf-pop": "LHR50-P6",
    "x-content-type-options": "nosniff",
    "age": "28410548",
    "x-cache": "Hit from cloudfront",
    "cache-control": "public, max-age=31536000, immutable"
  },
  "url": "https://deno.land/std@0.132.0/node/_fs/_fs_read.ts",
  "now": {
    "secs_since_epoch": 1726999292,
    "nanos_since_epoch": 518064793
  }
}