{
  "headers": {
    "x-amz-cf-pop": "LHR50-P6",
    "x-amz-replication-status": "COMPLETED",
    "cross-origin-opener-policy": "same-origin",
    "access-control-allow-origin": "*",
    "cross-origin-embedder-policy": "same-origin",
    "x-content-type-options": "nosniff",
    "x-frame-options": "DENY",
    "referrer-policy": "strict-origin-when-cross-origin",
    "x-amz-cf-id": "THjC6ztKJDmurM_ZLGeY1CjfyIaGboCT51HLq4_6PYOH-2xuypRwbA==",
    "etag": "W/\"b66931488aaeef85f9733a095262752c\"",
    "cache-control": "public, max-age=31536000, immutable",
    "strict-transport-security": "max-age=63072000; includeSubDomains; preload",
    "server-timing": "fetchSource;dur=6",
    "server": "deno/gcp-europe-west2",
    "vary": "Accept-Encoding, Origin",
    "last-modified": "Fri, 25 Mar 2022 13:32:48 GMT",
    "content-type": "application/javascript",
    "age": "28592774",
    "content-security-policy": "default-src 'none'; style-src 'unsafe-inline'; sandbox",
    "date": "Fri, 27 Oct 2023 11:35:31 GMT",
    "x-amz-version-id": "dp_2bZQMDIQ9pa18V2gAn6nYGQXiJTtd",
    "x-cache": "Hit from cloudfront",
    "cross-origin-resource-policy": "same-origin",
    "via": "http/2 edgeproxy-h"
  },
  "url": "https://deno.land/std@0.132.0/node/_crypto/crypto_browserify/asn1.js/mod.js",
  "now": {
    "secs_since_epoch": 1726999293,
    "nanos_since_epoch": 449529710
  }
}