{
  "headers": {
    "server": "deno/gcp-europe-west2",
    "content-security-policy": "default-src 'none'; style-src 'unsafe-inline'; sandbox",
    "server-timing": "fetchSource;dur=6",
    "x-frame-options": "DENY",
    "x-amz-cf-id": "sb9hJxPo8JrfzKeqqc_padtlfgfyilH21QTwhZJJJCVxDCeyA6_AGA==",
    "content-type": "application/javascript",
    "x-amz-replication-status": "COMPLETED",
    "date": "Mon, 25 Mar 2024 15:34:56 GMT",
    "x-amz-server-side-encryption": "AES256",
    "via": "http/2 edgeproxy-h",
    "x-amz-version-id": "RVJccRhP6FN5nw5lp4cbraG1kxaz6eRL",
    "strict-transport-security": "max-age=63072000; includeSubDomains; preload",
    "age": "15618406",
    "referrer-policy": "strict-origin-when-cross-origin",
    "cross-origin-embedder-policy": "same-origin",
    "x-amz-cf-pop": "LHR50-P6",
    "x-content-type-options": "nosniff",
    "cross-origin-opener-policy": "same-origin",
    "vary": "Accept-Encoding, Origin",
    "etag": "W/\"98b67f6b66f29088ef388e1eb9ad7999\"",
    "x-cache": "Hit from cloudfront",
    "last-modified": "Thu, 21 Mar 2024 20:52:12 GMT",
    "cache-control": "public, max-age=31536000, immutable",
    "cross-origin-resource-policy": "same-origin",
    "access-control-allow-origin": "*"
  },
  "url": "https://deno.land/x/postgresjs@v3.4.4/src/query.js",
  "now": {
    "secs_since_epoch": 1726999290,
    "nanos_since_epoch": 538855417
  }
}