{
  "headers": {
    "accept-ranges": "bytes",
    "content-security-policy": "default-src 'none'; style-src 'unsafe-inline'; sandbox",
    "vary": "Accept-Encoding, Origin",
    "cross-origin-resource-policy": "same-origin",
    "via": "http/2 edgeproxy-h",
    "strict-transport-security": "max-age=63072000; includeSubDomains; preload",
    "age": "18613705",
    "x-frame-options": "DENY",
    "content-length": "87",
    "cross-origin-embedder-policy": "same-origin",
    "access-control-allow-origin": "*",
    "last-modified": "Fri, 25 Mar 2022 13:32:50 GMT",
    "x-amz-replication-status": "COMPLETED",
    "x-content-type-options": "nosniff",
    "x-amz-cf-id": "WQtpBuMUs4Syzfmmy0Upk1dUVSbphR3IAtwve8N6m6yzQgVCJJhJZQ==",
    "cache-control": "public, max-age=31536000, immutable",
    "cross-origin-opener-policy": "same-origin",
    "server": "deno/gcp-europe-west2",
    "server-timing": "fetchSource;dur=24",
    "x-amz-cf-pop": "LHR50-P6",
    "x-amz-version-id": "QYvivPSZeZ1Pq8FfbaHxfj5DEp1IWjUH",
    "date": "Wed, 21 Feb 2024 05:08:54 GMT",
    "referrer-policy": "strict-origin-when-cross-origin",
    "x-cache": "Hit from cloudfront",
    "content-type": "application/typescript; charset=utf-8",
    "etag": "\"fcedf961bc626fd76a0c85089f1afb10\""
  },
  "url": "https://deno.land/std@0.132.0/node/internal_binding/tls_wrap.ts",
  "now": {
    "secs_since_epoch": 1727105828,
    "nanos_since_epoch": 796493876
  }
}