{
  "headers": {
    "cross-origin-embedder-policy": "same-origin",
    "last-modified": "Fri, 25 Mar 2022 13:32:50 GMT",
    "cross-origin-resource-policy": "same-origin",
    "referrer-policy": "strict-origin-when-cross-origin",
    "via": "http/2 edgeproxy-h",
    "server": "deno/gcp-europe-west2",
    "x-amz-cf-pop": "LHR50-P6",
    "cache-control": "public, max-age=31536000, immutable",
    "strict-transport-security": "max-age=63072000; includeSubDomains; preload",
    "content-security-policy": "default-src 'none'; style-src 'unsafe-inline'; sandbox",
    "accept-ranges": "bytes",
    "etag": "\"f64e5a547f38ba194ecc5bfa5c00c8c7\"",
    "access-control-allow-origin": "*",
    "content-length": "3494",
    "cross-origin-opener-policy": "same-origin",
    "date": "Sun, 29 Oct 2023 14:12:36 GMT",
    "content-type": "application/typescript; charset=utf-8",
    "vary": "Accept-Encoding, Origin",
    "x-amz-version-id": "b4yC_Blba0txCOWZwjc.Fpuy_yCjiZty",
    "age": "27483632",
    "x-amz-cf-id": "F6kNy_XI35umQlfiTLcYBqP1xqzL6FE32dHAdXqshLLy_OV2U_lZ2Q==",
    "x-cache": "Hit from cloudfront",
    "x-content-type-options": "nosniff",
    "x-amz-replication-status": "COMPLETED",
    "x-frame-options": "DENY",
    "server-timing": "fetchSource;dur=14"
  },
  "url": "https://deno.land/std@0.132.0/node/internal_binding/buffer.ts",
  "now": {
    "secs_since_epoch": 1726072377,
    "nanos_since_epoch": 680036468
  }
}