{
  "headers": {
    "age": "27673864",
    "x-frame-options": "DENY",
    "content-length": "9833",
    "date": "Fri, 27 Oct 2023 09:22:05 GMT",
    "cross-origin-resource-policy": "same-origin",
    "etag": "\"9226ae38d669dc9a1557e7ecfcd85e75\"",
    "cross-origin-embedder-policy": "same-origin",
    "accept-ranges": "bytes",
    "server-timing": "fetchSource;dur=16",
    "vary": "Accept-Encoding, Origin",
    "x-cache": "Hit from cloudfront",
    "via": "http/2 edgeproxy-h",
    "x-amz-cf-pop": "LHR50-P6",
    "referrer-policy": "strict-origin-when-cross-origin",
    "cache-control": "public, max-age=31536000, immutable",
    "content-security-policy": "default-src 'none'; style-src 'unsafe-inline'; sandbox",
    "access-control-allow-origin": "*",
    "content-type": "application/typescript; charset=utf-8",
    "x-amz-cf-id": "HenN6fOsJ0X-cCoKYIv_zlzkE5tDbtSo3sPoRZrsY2ZG1Qzoeg235Q==",
    "last-modified": "Fri, 25 Mar 2022 13:32:47 GMT",
    "server": "deno/gcp-europe-west2",
    "x-amz-replication-status": "COMPLETED",
    "x-content-type-options": "nosniff",
    "x-amz-version-id": "0OJumtLeKOVrsGcPz_8vxnLzUq4eW_yr",
    "strict-transport-security": "max-age=63072000; includeSubDomains; preload",
    "cross-origin-opener-policy": "same-origin"
  },
  "url": "https://deno.land/std@0.132.0/flags/mod.ts",
  "now": {
    "secs_since_epoch": 1726072378,
    "nanos_since_epoch": 166050176
  }
}